shiny_treeview/__init__.py
shiny_treeview/__version__.py
shiny_treeview/playwright.py
shiny_treeview/stratify.py
shiny_treeview/tree.py
shiny_treeview/ui.py
shiny_treeview/utils.py
shiny_treeview/distjs/index.js
shiny_treeview-0.1.1.dist-info/licenses/LICENSE
shiny_treeview-0.1.1.dist-info/METADATA
shiny_treeview-0.1.1.dist-info/WHEEL
shiny_treeview-0.1.1.dist-info/top_level.txt
shiny_treeview-0.1.1.dist-info/RECORD
