Metadata-Version: 2.4
Name: shiny-treeview
Version: 0.1.1
Summary: A Shiny for Python extension providing a treeview component
Author-email: David Hall <david.hall.physics@gmail.com>
License: MIT License
Project-URL: Homepage, https://github.com/davidchall/shiny-treeview
Project-URL: Documentation, https://davidchall.github.io/shiny-treeview
Project-URL: Repository, https://github.com/davidchall/shiny-treeview.git
Project-URL: Bug Tracker, https://github.com/davidchall/shiny-treeview/issues
Keywords: shiny,python,treeview
Classifier: Development Status :: 4 - Beta
Classifier: Intended Audience :: Developers
Classifier: License :: OSI Approved :: MIT License
Classifier: Operating System :: OS Independent
Classifier: Programming Language :: Python :: 3
Classifier: Programming Language :: Python :: 3.10
Classifier: Programming Language :: Python :: 3.11
Classifier: Programming Language :: Python :: 3.12
Classifier: Programming Language :: Python :: 3.13
Classifier: Topic :: Internet :: WWW/HTTP :: Dynamic Content
Classifier: Topic :: Software Development :: Libraries :: Python Modules
Classifier: Topic :: Software Development :: User Interfaces
Classifier: Topic :: Scientific/Engineering :: Visualization
Requires-Python: >=3.10
License-File: LICENSE
Requires-Dist: shiny>=0.6.0
Requires-Dist: htmltools>=0.6.0
Provides-Extra: test
Requires-Dist: pytest; extra == "test"
Requires-Dist: playwright; extra == "test"
Requires-Dist: pytest-playwright; extra == "test"
Requires-Dist: pytest-playwright-visual-snapshot; extra == "test"
Provides-Extra: docs
Requires-Dist: quartodoc; extra == "docs"
Requires-Dist: shinylive; extra == "docs"
Provides-Extra: dev
Requires-Dist: shiny-treeview[docs,test]; extra == "dev"
Requires-Dist: black; extra == "dev"
Requires-Dist: flake8; extra == "dev"
Requires-Dist: isort; extra == "dev"
Dynamic: license-file
